.travis.yml
AUTHORS.rst
HISTORY.rst
LICENSE.txt
MANIFEST.in
README.rst
requirements.txt
setup.cfg
setup.py
tox.ini
lazgui/__init__.py
lazgui/_version.py
lazgui/button.py
lazgui/checkbox.py
lazgui/edit.py
lazgui/form.py
lazgui/gui_factory.py
lazgui/ini_supt.py
lazgui/label.py
lazgui/labeled_edit.py
lazgui/layout.py
lazgui/laz_gui.py
lazgui/laz_snippets.py
lazgui/listbox.py
lazgui/lpi_wrapper.py
lazgui/lpr_wrapper.py
lazgui/lps_wrapper.py
lazgui/page_control.py
lazgui/panel.py
lazgui/radio_group.py
lazgui/widget.py
lazgui.egg-info/PKG-INFO
lazgui.egg-info/SOURCES.txt
lazgui.egg-info/dependency_links.txt
lazgui.egg-info/not-zip-safe
lazgui.egg-info/pbr.json
lazgui.egg-info/requires.txt
lazgui.egg-info/top_level.txt
lazgui/examples/example_1.py
lazgui/examples/example_2.py
lazgui/examples/example_3.py
lazgui/examples/example_4.py
lazgui/examples/example_lab_1.py
lazgui/examples/factory_pagecontrol.py
lazgui/examples/factory_panel.py
lazgui/examples/factory_v1.py
lazgui/examples/factory_v2.py
lazgui/ref_proj_files/HistoryFiles.pas
lazgui/ref_proj_files/HistoryLazarus.lrs
lazgui/ref_proj_files/chk_etree.py
lazgui/ref_proj_files/get_set_io_var.pas
lazgui/ref_proj_files/project1.ico
lazgui/ref_proj_files/project1.lpi
lazgui/ref_proj_files/project1.lpr
lazgui/ref_proj_files/project1.lps
lazgui/ref_proj_files/project1.res
lazgui/ref_proj_files/unit1.lfm
lazgui/ref_proj_files/unit1.pas
lazgui/tests/__init__.py
lazgui/tests/test_laz_gui.py
lazgui/tests/chk_factory/HistoryFiles.pas
lazgui/tests/chk_factory/HistoryLazarus.lrs
lazgui/tests/chk_factory/ProjWhat.bat
lazgui/tests/chk_factory/ProjWhat.exe
lazgui/tests/chk_factory/ProjWhat.ico
lazgui/tests/chk_factory/ProjWhat.lpi
lazgui/tests/chk_factory/ProjWhat.lpi.bak
lazgui/tests/chk_factory/ProjWhat.lpr
lazgui/tests/chk_factory/ProjWhat.lps
lazgui/tests/chk_factory/ProjWhat.lps.bak
lazgui/tests/chk_factory/ProjWhat.res
lazgui/tests/chk_factory/get_set_io_var.pas
lazgui/tests/chk_factory/get_set_io_var.pas.bak
lazgui/tests/chk_factory/myform1_unit.lfm
lazgui/tests/chk_factory/myform1_unit.lfm.bak
lazgui/tests/chk_factory/myform1_unit.pas
lazgui/tests/chk_factory/myform1_unit.pas.bak
